{
    "name_ru": "Триптих",
    "name_en": "Triptych",
    "base": "холст",
    "material": "масло",
    "size": "",
    "year": "2020",
    "price": "30000",
    "parts": [
        {
            "name_ru": "Пленер за городом, часть 1",
            "name_en": "Plein air outside the city, part 1",
            "base": "холст",
            "material": "масло",
            "size": "30x40"
        },
        {
            "name_ru": "Пленер за городом, часть 1",
            "name_en": "Plein air outside the city, part 1",
            "base": "холст",
            "material": "масло",
            "size": "30x40"
        },
        {
            "name_ru": "Пленер за городом, часть 2",
            "name_en": "Plein air outside the city, part 2",
            "base": "холст",
            "material": "масло",
            "size": "35x25"
        },
        {
            "name_ru": "Пленер за городом, часть 2",
            "name_en": "Plein air outside the city, part 2",
            "base": "холст",
            "material": "масло",
            "size": "35x25"
        },
        {
            "name_ru": "Пленер за городом, часть 3",
            "name_en": "Plein air outside the city, part 3",
            "base": "холст",
            "material": "масло",
            "size": "30x40"
        },
        {
            "name_ru": "Пленер за городом, часть 3",
            "name_en": "Plein air outside the city, part 3",
            "base": "холст",
            "material": "масло",
            "size": "30x40"
        }
    ]
}